xregi/__init__.py
xregi/__main__.py
xregi/args.py
xregi/config.py
xregi/landmark_container.py
xregi/landmark_detector.py
xregi/registration_2d_3d.py
xregi/registration_solver.py
xregi/setup-our.py
xregi/utils.py
xregi/vis_utils.py
xregi/synthex/__init__.py
xregi/synthex/class_ensemble.py
xregi/synthex/dataset.py
xregi/synthex/dice.py
xregi/synthex/est_land_csv.py
xregi/synthex/ncc.py
xregi/synthex/test_ensemble.py
xregi/synthex/util.py
xregi/synthex/TransUNet/__init__.py
xregi/synthex/TransUNet/transunet.py
xregi/synthex/TransUNet/vit_seg_configs.py
xregi/synthex/TransUNet/vit_seg_modeling.py
xregi/synthex/TransUNet/vit_seg_modeling_resnet_skip.py
xregi-0.3.4.dist-info/LICENSE
xregi-0.3.4.dist-info/METADATA
xregi-0.3.4.dist-info/WHEEL
xregi-0.3.4.dist-info/top_level.txt
xregi-0.3.4.dist-info/RECORD
